switchedon/__init__.py
switchedon/parse.py
switchedon-0.1.1.dist-info/METADATA
switchedon-0.1.1.dist-info/WHEEL
switchedon-0.1.1.dist-info/entry_points.txt
switchedon-0.1.1.dist-info/top_level.txt
switchedon-0.1.1.dist-info/RECORD
